venvception/__init__.py
venvception/venv.py
venvception/version.py
venvception-0.0.5.dist-info/LICENSE
venvception-0.0.5.dist-info/METADATA
venvception-0.0.5.dist-info/WHEEL
venvception-0.0.5.dist-info/top_level.txt
venvception-0.0.5.dist-info/RECORD
