Metadata-Version: 2.1
Name: venvception
Version: 0.0.5
Summary: Install requirements and run code in virtual environments from the comfort of your own GIL
Author-email: Nathan Zimmerman <npzimmerman@gmail.com>
License: MIT
Project-URL: homepage, https://github.com/moradology/venvception
Project-URL: repository, https://github.com/moradology/venvception.git
Keywords: virtualenv,dependencies
Classifier: Intended Audience :: Developers
Classifier: Intended Audience :: Information Technology
Classifier: Intended Audience :: Science/Research
Classifier: Programming Language :: Python :: 3.8
Classifier: Programming Language :: Python :: 3.9
Classifier: Programming Language :: Python :: 3.10
Classifier: Programming Language :: Python :: 3.11
Classifier: License :: OSI Approved :: MIT License
Requires-Python: >=3.8
License-File: LICENSE
Provides-Extra: dev
Requires-Dist: pytest >=8.0.0 ; extra == 'dev'
Requires-Dist: pytest-cov >=4.1.0 ; extra == 'dev'
Provides-Extra: lint
Requires-Dist: black >=23.9.1 ; extra == 'lint'
Requires-Dist: isort >=5.13.0 ; extra == 'lint'
Requires-Dist: flake8 >=7.0.0 ; extra == 'lint'
Requires-Dist: Flake8-pyproject >=1.2.3 ; extra == 'lint'
Requires-Dist: mypy >=1.8.0 ; extra == 'lint'
Requires-Dist: pre-commit >=3.4.0 ; extra == 'lint'
Requires-Dist: pytest >=8.0.0 ; extra == 'lint'
Requires-Dist: pytest-cov >=4.1.0 ; extra == 'lint'
Requires-Dist: tox >=4.11.3 ; extra == 'lint'
